{
  "main": {
    "name": "Matthew Ouyang",
    "occupation": "Software Engineer",
    "description": "",
    "image": "profilepic.jpg",
    "bio": "I have always been interested in technology and it's importance in the world. It started in high school Mechatronics class where we built and programmed robots using micro controllers. It was then I discovered my passion for coding and engineering. I enjoy problem solving and automating the world around you through software programming. I am excited for the future prospect of software in AI, Cloud Computing, Autonomous vehicles and space travel. These are some of the many feilds I'm hungry to pursue. Throughout my career I want to make a positive and lasting impact on people for many generations to come.",
    "contactmessage": "I look forward discussing an exciting opportunity with you.  Please feel free to contact me.",
    "email": "mouyang2001@gmail.com",
    "phone": "(+64) 22 311 3644",
    "address": {
      "city": "Auckland",
      "country": "New Zealand",
      "zip": "0600"
    },
    "website": "http://www.google.com",
    "resumedownload": "https://drive.google.com/file/d/1t7GDR5wPSuu40Njmkt0p4TTWIJvFjVcY/view?usp=sharing",
    "social": [
      {
        "name": "linkedin",
        "url": "https://www.linkedin.com/in/matthew-ouyang-7a732719b/",
        "className": "fa fa-linkedin"
      },
      {
        "name": "github",
        "url": "https://github.com/mouyang2001",
        "className": "fa fa-github"
      }
    ]
  },
  "resume": {
    "skillmessage": "My Technical skills",
    "education": [
      {
        "school": "University of Auckland",
        "degree": "Bachelor of Engineering",
        "graduated": "2020-2023",
        "description": "Achieved a cumulative GPA of 8.6 / 9 to date and included on the Dean’s Honours List 2020. University tour guide and new student mentor (Feb-Mar 2021). Active member of the University’s Muay Thai club and Kiwi Asian social club."
      }
    ],
    "work": [
      {
        "company": "Web Development Consulting Club",
        "title": "Web Developer ",
        "years": "May 2021 - Present",
        "description": "Develop and maintain the Auckland student pool association's event and registration app."
      },
      {
        "company": "Mcdonalds",
        "title": "Crew Member",
        "years": "December 2018 - Januaury 2020",
        "description": "Received the Employee of the Month Award in January and February 2019 for consistently exceeded monthly KPIs and maintaining customer satisfaction ratings. Due to outstanding performance and demonstrating strong leadership/hospitality skills, given further responsibility for managing the kitchen in an unsupervised capacity.Developed and taught crew members new efficient methods of preparing food, which in turn led to exceeding monthly KPI targets."
      }
    ],
    "skills": [
      {
        "name": "Git",
        "level": "60%"
      },
      {
        "name": "Javascript",
        "level": "55%"
      },
      {
        "name": "ReactJs",
        "level": "50%"
      },
      {
        "name": "CSS",
        "level": "90%"
      },
      {
        "name": "HTML5",
        "level": "80%"
      },
      {
        "name": "Java",
        "level": "50%"
      },
      {
        "name": "Matlab",
        "level": "80%"
      },
      {
        "name": "Python",
        "level": "80%"
      }
    ]
  },
  "portfolio": {
    "projects": [
      {
        "title": "Event Registration & Payment",
        "category": "Auckland Student Pool Association event registration and payment app.",
        "image": "aspa.jpg",
        "url": "https://aspa.wdcc.co.nz/"
      },
      {
        "title": "Virtual Team Pet",
        "category": "DEVS Hackathon 1st place app. Virtual team pet to promote good coding practices.",
        "image": "developets.png",
        "url": "https://developets-client.herokuapp.com"
      },
      {
        "title": "Small business lead generation",
        "category": "MYOB IT challenge small business lead generation web app prototype. Top 3 NZ.",
        "image": "genie.jpg",
        "url": "https://genie-app-digital.herokuapp.com/"
      },
      {
        "title": "Android messaging app",
        "category": "Add friends, send messages and photos.",
        "image": "clique.jpg",
        "url": "https://github.com/mouyang2001/Clique"
      },
      {
        "title": "Social note sharing",
        "category": "Take notes and share with others. Like comment and recieve notfications.",
        "image": "jotter.jpg",
        "url": "https://jotter-8af9d.web.app/"
      },
      {
        "title": "Traffic Jam terminal game",
        "category": "Simulate the game of traffic jam within the terminal, university project.",
        "image": "trafficjam.jpg",
        "url": "https://www.onlinegdb.com/HJT5U_DGO"
      }
    ]
  },
  "testimonials": {
    "testimonials": [
      {
        "text": "Here you should write some nice things that someone has said about you. No lies though, employers can tell when you are lying.",
        "user": "Kareem Abdul Jabbar"
      },
      {
        "text": "That Tim Baker must be one of the most brilliant developers I've ever met! It is amazing that nobody has hired him yet. Hey you, you should hire this guy, he may be fresh out of University and have zero on the job experience but I am confident that he will be one of your best developers in no time!",
        "user": "Steve Wozniak... impersonator"
      }
    ]
  }
}
